README.md
setup.py
sentry_dingtalk/__init__.py
sentry_dingtalk/plugin.py
sentry_dingtalk_bot.egg-info/PKG-INFO
sentry_dingtalk_bot.egg-info/SOURCES.txt
sentry_dingtalk_bot.egg-info/dependency_links.txt
sentry_dingtalk_bot.egg-info/entry_points.txt
sentry_dingtalk_bot.egg-info/not-zip-safe
sentry_dingtalk_bot.egg-info/requires.txt
sentry_dingtalk_bot.egg-info/top_level.txt