Metadata-Version: 2.1
Name: sentry-dingtalk-bot
Version: 1.4.2
Summary: A Sentry extension which integrates with Dingtalk robot.
Home-page: https://github.com/liupcoder/sentry_dingtalk_bot.git
Author: lpcoder
Author-email: liupcoder@126.com
License: BSD
Keywords: sentry dingding dingtalk
Platform: any
Classifier: Framework :: Django
Classifier: Intended Audience :: Developers
Classifier: Intended Audience :: System Administrators
Classifier: Operating System :: OS Independent
Classifier: Topic :: Software Development
Provides-Extra: test
